aoc_helper/__init__.py
aoc_helper/__main__.py
aoc_helper/data.py
aoc_helper/day_template.py
aoc_helper/formatting.py
aoc_helper/interface.py
aoc_helper/main.py
aoc_helper/types.py
aoc_helper/utils.py
aoc_helper-1.14.0.dist-info/LICENSE
aoc_helper-1.14.0.dist-info/METADATA
aoc_helper-1.14.0.dist-info/WHEEL
aoc_helper-1.14.0.dist-info/entry_points.txt
aoc_helper-1.14.0.dist-info/top_level.txt
aoc_helper-1.14.0.dist-info/RECORD
