Metadata-Version: 2.1
Name: aoc-helper
Version: 1.14.0
Summary: A helper package for Advent of Code
Author: Starwort, salt-die
Project-URL: Homepage, https://github.com/Starwort/aoc_helper
Classifier: Programming Language :: Python :: 3
Classifier: License :: OSI Approved :: MIT License
Classifier: Operating System :: OS Independent
Requires-Python: >=3.9
License-File: LICENSE
Requires-Dist: requests
Requires-Dist: beautifulsoup4
Requires-Dist: typing-extensions
Provides-Extra: cli
Requires-Dist: click ; extra == 'cli'
Requires-Dist: click-aliases ; extra == 'cli'
Provides-Extra: fancy
Requires-Dist: rich ; extra == 'fancy'
Provides-Extra: full
Requires-Dist: click ; extra == 'full'
Requires-Dist: click-aliases ; extra == 'full'
Requires-Dist: rich ; extra == 'full'
